{"analysisResults":[[{"matchingRatio":0.8742485046386719,"averageDistanceRatio":0.001654719069132756,"mismatchingAverageDistanceRatio":0.013158643277983837},{"matchingRatio":0.9068603515625,"averageDistanceRatio":0.0016516141065898535,"mismatchingAverageDistanceRatio":0.017761061159229798},{"matchingRatio":0.9659080505371094,"averageDistanceRatio":0.0015240436894245581,"mismatchingAverageDistanceRatio":0.047543616293072154}],[{"matchingRatio":0.077362060546875,"averageDistanceRatio":0.0017818878121065864,"mismatchingAverageDistanceRatio":0.0019312969214801252},{"matchingRatio":0.18019866943359375,"averageDistanceRatio":0.001757148841834471,"mismatchingAverageDistanceRatio":0.002171780729758223},{"matchingRatio":0.9625911712646484,"averageDistanceRatio":0.0014345733662737955,"mismatchingAverageDistanceRatio":0.04118822298400223}]],"lighting":"../../../shared-assets/environments/lightroom_14b.hdr","dimensions":{"width":512,"height":1024},"target":{"x":0,"y":3.6,"z":0},"orbit":{"theta":0,"phi":90,"radius":11.2},"verticalFoV":45,"name":"khronos-AntiqueCamera","model":"../../../shared-assets/models/glTF-Sample-Models/2.0/AntiqueCamera/glTF/AntiqueCamera.gltf"}